{
    "default": {
        "name": "Epipelagic",
        "background": "ocean",
        "icon": "res://assets/textures/gui/bevel/epipelagic.png",
        "skybox": "Thrive_ocean_skybox",
        "skyboxLightIntensity": 0.5,
        "sunlight": {
            "color": {
                "r": 1,
                "g": 1,
                "b": 1
            },
            "intensity": 0.0001,
            "direction": {
                "x": 0.55,
                "y": -0.3,
                "z": 0.75
            },
            "sourceRadius": 0.5
        },
        "eyeAdaptation": {
            "min": 0.003,
            "max": 2
        },
        "chunks": {
            "floatingToxin": {
                "name": "Floating Hazard",
                "meshes": [
                    {
                        "scenePath": "res://assets/models/organelles/OxytoxyProteins.tscn"
                    }
                ],
                "density": 0.0001,
                "dissolves": false,
                "radius": 1,
                "chunkScale": 1,
                "mass": 7,
                "size": 10000,
                "ventAmount": 3,
                "damages": 10,
                "deleteOnTouch": true,
                "compounds": {}
            },
            "ironSmallChunk": {
                "name": "Small Iron Chunk",
                "meshes": [
                    {
                        "scenePath": "res://assets/models/IronRock1.tscn"
                    },
                    {
                        "scenePath": "res://assets/models/IronRock2.tscn"
                    },
                    {
                        "scenePath": "res://assets/models/Iron3.tscn"
                    },
                    {
                        "scenePath": "res://assets/models/Iron4.tscn"
                    }
                ],
                "density": 0,
                "dissolves": true,
                "radius": 1,
                "chunkScale": 1,
                "mass": 100,
                "size": 2,
                "ventAmount": 6,
                "damages": 0,
                "deleteOnTouch": false,
                "compounds": {
                    "iron": {
                        "amount": 200
                    }
                }
            },
            "ironBigChunk": {
                "name": "Big Iron Chunk",
                "meshes": [
                    {
                        "scenePath": "res://assets/models/Iron5.tscn"
                    }
                ],
                "density": 0,
                "dissolves": true,
                "radius": 10,
                "chunkScale": 1,
                "mass": 100,
                "size": 100,
                "ventAmount": 20,
                "damages": 0,
                "deleteOnTouch": false,
                "compounds": {
                    "iron": {
                        "amount": 60000
                    }
                }
            }
        },
        "averageTemperature": 8,
        "compounds": {
            "ammonia": {
                "amount": 200000,
                "density": 0.00002,
                "dissolved": 0
            },
            "glucose": {
                "amount": 250000,
                "density": 0.00002,
                "dissolved": 0
            },
            "phosphates": {
                "amount": 200000,
                "density": 0.00002,
                "dissolved": 0
            },
            "hydrogensulfide": {
                "amount": 0,
                "density": 0,
                "dissolved": 0
            },
            "oxygen": {
                "amount": 0,
                "density": 0,
                "dissolved": 0.21
            },
            "carbondioxide": {
                "amount": 0,
                "density": 0,
                "dissolved": 0.09
            },
            "nitrogen": {
                "amount": 0,
                "density": 0,
                "dissolved": 0.7
            },
            "sunlight": {
                "amount": 0,
                "density": 0,
                "dissolved": 1
            }
        }
    },
    "aavolcanic_vent": {
        "name": "Volcanic vent",
        "background": "vent",
        "icon": "res://assets/textures/gui/bevel/vents.png",
        "skybox": "Thrive_vent_skybox",
        "skyboxLightIntensity": 0.5,
        "sunlight": {
            "color": {
                "r": 1,
                "g": 1,
                "b": 1
            },
            "intensity": 0.0001,
            "direction": {
                "x": 0.55,
                "y": -0.3,
                "z": 0.75
            },
            "sourceRadius": 0.5
        },
        "eyeAdaptation": {
            "min": 0.003,
            "max": 0.8
        },
        "chunks": {
            "floatingToxin": {
                "name": "Floating Hazard",
                "meshes": [
                    {
                        "scenePath": "res://assets/models/organelles/OxytoxyProteins.tscn"
                    }
                ],
                "density": 0.0001,
                "dissolves": false,
                "radius": 1,
                "chunkScale": 1,
                "mass": 7,
                "size": 10000,
                "ventAmount": 3,
                "damages": 10,
                "deleteOnTouch": true,
                "compounds": {}
            },
            "ironSmallChunk": {
                "name": "Small Iron Chunk",
                "meshes": [
                    {
                        "scenePath": "res://assets/models/IronRock1.tscn"
                    },
                    {
                        "scenePath": "res://assets/models/IronRock2.tscn"
                    },
                    {
                        "scenePath": "res://assets/models/Iron3.tscn"
                    },
                    {
                        "scenePath": "res://assets/models/Iron4.tscn"
                    }
                ],
                "density": 0.00005,
                "dissolves": true,
                "radius": 1,
                "chunkScale": 1,
                "mass": 100,
                "size": 2,
                "ventAmount": 6,
                "damages": 0,
                "deleteOnTouch": false,
                "compounds": {
                    "iron": {
                        "amount": 200
                    }
                }
            },
            "marineSnow": {
                "name": "Marine snow",
                "meshes": [
                    {
                        "scenePath": "res://assets/models/organelles/Oxytoxy.tscn"
                    },
                    {
                        "scenePath": "res://assets/models/organelles/Nucleus.tscn"
                    },
                    {
                        "scenePath": "res://assets/models/organelles/Chloroplast.tscn"
                    },
                    {
                        "scenePath": "res://assets/models/organelles/OxytoxyProteins.tscn"
                    },
                    {
                        "scenePath": "res://assets/models/organelles/Flagellum.tscn"
                    },
                    {
                        "scenePath": "res://assets/models/organelles/Chemoplast.tscn"
                    },
                    {
                        "scenePath": "res://assets/models/organelles/NitrogenFixingPlastid.tscn"
                    },
                    {
                        "scenePath": "res://assets/models/organelles/Metabolosome.tscn"
                    },
                    {
                        "scenePath": "res://assets/models/organelles/Chromatophore.tscn"
                    },
                    {
                        "scenePath": "res://assets/models/organelles/Vacuole.tscn"
                    },
                    {
                        "scenePath": "res://assets/models/organelles/Mitochondrion.tscn"
                    },
                    {
                        "scenePath": "res://assets/models/organelles/ChemoSynthesizingProteins.tscn"
                    },
                    {
                        "scenePath": "res://assets/models/organelles/Nitrogenase.tscn"
                    },
                    {
                        "scenePath": "res://assets/models/organelles/Rusticyanin.tscn"
                    }
                ],
                "density": 0,
                "dissolves": true,
                "radius": 1,
                "chunkScale": 1,
                "mass": 7,
                "size": 2,
                "ventAmount": 3,
                "damages": 0,
                "deleteOnTouch": false,
                "compounds": {
                    "atp": {
                        "amount": 100
                    },
                    "ammonia": {
                        "amount": 100
                    },
                    "phosphates": {
                        "amount": 100
                    },
                    "glucose": {
                        "amount": 100
                    }
                }
            },
            "ironBigChunk": {
                "name": "Big Iron Chunk",
                "meshes": [
                    {
                        "scenePath": "res://assets/models/Iron5.tscn"
                    }
                ],
                "density": 0.00005,
                "dissolves": true,
                "radius": 10,
                "chunkScale": 1,
                "mass": 100,
                "size": 100,
                "ventAmount": 20,
                "damages": 0,
                "deleteOnTouch": false,
                "compounds": {
                    "iron": {
                        "amount": 60000
                    }
                }
            }
        },
        "averageTemperature": 98,
        "compounds": {
            "ammonia": {
                "amount": 300000,
                "density": 0.00004,
                "dissolved": 0
            },
            "glucose": {
                "amount": 250000,
                "density": 0.00002,
                "dissolved": 0
            },
            "phosphates": {
                "amount": 300000,
                "density": 0.00004,
                "dissolved": 0
            },
            "hydrogensulfide": {
                "amount": 300000,
                "density": 0.00004,
                "dissolved": 0
            },
            "oxygen": {
                "amount": 0,
                "density": 0,
                "dissolved": 0.21
            },
            "carbondioxide": {
                "amount": 0,
                "density": 0,
                "dissolved": 0.09
            },
            "nitrogen": {
                "amount": 0,
                "density": 0,
                "dissolved": 0.7
            },
            "sunlight": {
                "amount": 0,
                "density": 0,
                "dissolved": 0
            }
        }
    },
    "tidepool": {
        "name": "Tidepool",
        "background": "tidepool",
        "icon": "res://assets/textures/gui/bevel/tidepool.png",
        "skybox": "Thrive_tidepool_skybox",
        "skyboxLightIntensity": 0.5,
        "sunlight": {
            "color": {
                "r": 1,
                "g": 1,
                "b": 1
            },
            "intensity": 0.0001,
            "direction": {
                "x": 0.55,
                "y": -0.3,
                "z": 0.75
            },
            "sourceRadius": 0.5
        },
        "eyeAdaptation": {
            "min": 0.003,
            "max": 2
        },
        "chunks": {
            "floatingToxin": {
                "name": "Floating Hazard",
                "meshes": [
                    {
                        "scenePath": "res://assets/models/organelles/OxytoxyProteins.tscn"
                    }
                ],
                "density": 0.0001,
                "dissolves": false,
                "radius": 1,
                "chunkScale": 1,
                "mass": 7,
                "size": 10000,
                "ventAmount": 3,
                "damages": 10,
                "deleteOnTouch": true,
                "compounds": {}
            },
            "ironSmallChunk": {
                "name": "Small Iron Chunk",
                "meshes": [
                    {
                        "scenePath": "res://assets/models/IronRock1.tscn"
                    },
                    {
                        "scenePath": "res://assets/models/IronRock2.tscn"
                    },
                    {
                        "scenePath": "res://assets/models/Iron3.tscn"
                    },
                    {
                        "scenePath": "res://assets/models/Iron4.tscn"
                    }
                ],
                "density": 0.00005,
                "dissolves": true,
                "radius": 1,
                "chunkScale": 1,
                "mass": 100,
                "size": 2,
                "ventAmount": 6,
                "damages": 0,
                "deleteOnTouch": false,
                "compounds": {
                    "iron": {
                        "amount": 200
                    }
                }
            },
            "ironBigChunk": {
                "name": "Big Iron Chunk",
                "meshes": [
                    {
                        "scenePath": "res://assets/models/Iron5.tscn"
                    }
                ],
                "density": 0.00005,
                "dissolves": true,
                "radius": 10,
                "chunkScale": 1,
                "mass": 100,
                "size": 100,
                "ventAmount": 20,
                "damages": 0,
                "deleteOnTouch": false,
                "compounds": {
                    "iron": {
                        "amount": 60000
                    }
                }
            }
        },
        "averageTemperature": 23,
        "compounds": {
            "ammonia": {
                "amount": 200000,
                "density": 0.00002,
                "dissolved": 0
            },
            "glucose": {
                "amount": 250000,
                "density": 0.00002,
                "dissolved": 0
            },
            "phosphates": {
                "amount": 200000,
                "density": 0.00002,
                "dissolved": 0
            },
            "hydrogensulfide": {
                "amount": 0,
                "density": 0,
                "dissolved": 0
            },
            "oxygen": {
                "amount": 0,
                "density": 0,
                "dissolved": 0.21
            },
            "carbondioxide": {
                "amount": 0,
                "density": 0,
                "dissolved": 0.09
            },
            "nitrogen": {
                "amount": 0,
                "density": 0,
                "dissolved": 0.7
            },
            "sunlight": {
                "amount": 0,
                "density": 0,
                "dissolved": 2
            }
        }
    },
    "bathypalagic": {
        "name": "Bathypalagic",
        "background": "bathypalagic",
        "icon": "res://assets/textures/gui/bevel/bathy.png",
        "skybox": "Thrive_bathy_skybox",
        "skyboxLightIntensity": 0.5,
        "sunlight": {
            "color": {
                "r": 1,
                "g": 1,
                "b": 1
            },
            "intensity": 0.0001,
            "direction": {
                "x": 0.55,
                "y": -0.3,
                "z": 0.75
            },
            "sourceRadius": 0.5
        },
        "eyeAdaptation": {
            "min": 0.003,
            "max": 1.5
        },
        "chunks": {
            "floatingToxin": {
                "name": "Floating Hazard",
                "meshes": [
                    {
                        "scenePath": "res://assets/models/organelles/OxytoxyProteins.tscn"
                    }
                ],
                "density": 0.00007,
                "dissolves": false,
                "radius": 1,
                "chunkScale": 1,
                "mass": 7,
                "size": 10000,
                "ventAmount": 3,
                "damages": 10,
                "deleteOnTouch": true,
                "compounds": {}
            },
            "ironSmallChunk": {
                "name": "Small Iron Chunk",
                "meshes": [
                    {
                        "scenePath": "res://assets/models/IronRock1.tscn"
                    },
                    {
                        "scenePath": "res://assets/models/IronRock2.tscn"
                    },
                    {
                        "scenePath": "res://assets/models/Iron3.tscn"
                    },
                    {
                        "scenePath": "res://assets/models/Iron4.tscn"
                    }
                ],
                "density": 0.00003,
                "dissolves": true,
                "radius": 1,
                "chunkScale": 1,
                "mass": 100,
                "size": 2,
                "ventAmount": 6,
                "damages": 0,
                "deleteOnTouch": false,
                "compounds": {
                    "iron": {
                        "amount": 200
                    }
                }
            },
            "ironBigChunk": {
                "name": "Big Iron Chunk",
                "meshes": [
                    {
                        "scenePath": "res://assets/models/Iron5.tscn"
                    }
                ],
                "density": 0.00003,
                "dissolves": true,
                "radius": 10,
                "chunkScale": 1,
                "mass": 100,
                "size": 100,
                "ventAmount": 20,
                "damages": 0,
                "deleteOnTouch": false,
                "compounds": {
                    "iron": {
                        "amount": 60000
                    }
                }
            },
            "marineSnow": {
                "name": "Marine snow",
                "meshes": [
                    {
                        "scenePath": "res://assets/models/organelles/Oxytoxy.tscn"
                    },
                    {
                        "scenePath": "res://assets/models/organelles/Nucleus.tscn"
                    },
                    {
                        "scenePath": "res://assets/models/organelles/Chloroplast.tscn"
                    },
                    {
                        "scenePath": "res://assets/models/organelles/OxytoxyProteins.tscn"
                    },
                    {
                        "scenePath": "res://assets/models/organelles/Flagellum.tscn"
                    },
                    {
                        "scenePath": "res://assets/models/organelles/Chemoplast.tscn"
                    },
                    {
                        "scenePath": "res://assets/models/organelles/NitrogenFixingPlastid.tscn"
                    },
                    {
                        "scenePath": "res://assets/models/organelles/Metabolosome.tscn"
                    },
                    {
                        "scenePath": "res://assets/models/organelles/Chromatophore.tscn"
                    },
                    {
                        "scenePath": "res://assets/models/organelles/Vacuole.tscn"
                    },
                    {
                        "scenePath": "res://assets/models/organelles/Mitochondrion.tscn"
                    },
                    {
                        "scenePath": "res://assets/models/organelles/ChemoSynthesizingProteins.tscn"
                    },
                    {
                        "scenePath": "res://assets/models/organelles/Nitrogenase.tscn"
                    },
                    {
                        "scenePath": "res://assets/models/organelles/Rusticyanin.tscn"
                    }
                ],
                "density": 0.0002,
                "dissolves": true,
                "radius": 1,
                "chunkScale": 1,
                "mass": 7,
                "size": 2,
                "ventAmount": 3,
                "damages": 0,
                "deleteOnTouch": false,
                "compounds": {
                    "atp": {
                        "amount": 100
                    },
                    "ammonia": {
                        "amount": 100
                    },
                    "phosphates": {
                        "amount": 100
                    },
                    "glucose": {
                        "amount": 100
                    }
                }
            }
        },
        "averageTemperature": 4,
        "compounds": {
            "ammonia": {
                "amount": 200000,
                "density": 0.00002,
                "dissolved": 0
            },
            "glucose": {
                "amount": 250000,
                "density": 0.00002,
                "dissolved": 0
            },
            "phosphates": {
                "amount": 200000,
                "density": 0.00002,
                "dissolved": 0
            },
            "hydrogensulfide": {
                "amount": 0,
                "density": 0,
                "dissolved": 0
            },
            "oxygen": {
                "amount": 0,
                "density": 0,
                "dissolved": 0.21
            },
            "carbondioxide": {
                "amount": 0,
                "density": 0,
                "dissolved": 0.09
            },
            "nitrogen": {
                "amount": 0,
                "density": 0,
                "dissolved": 0.7
            },
            "sunlight": {
                "amount": 0,
                "density": 0,
                "dissolved": 0
            }
        }
    },
    "abyssopelagic": {
        "name": "Abyssopelagic",
        "background": "abyssopelagic",
        "icon": "res://assets/textures/gui/bevel/abyss.png",
        "skybox": "Thrive_abyss_skybox",
        "skyboxLightIntensity": 0.5,
        "sunlight": {
            "color": {
                "r": 1,
                "g": 1,
                "b": 1
            },
            "intensity": 0.0001,
            "direction": {
                "x": 0.55,
                "y": -0.3,
                "z": 0.75
            },
            "sourceRadius": 0.5
        },
        "eyeAdaptation": {
            "min": 0.003,
            "max": 0.8
        },
        "chunks": {
            "floatingToxin": {
                "name": "Floating Hazard",
                "meshes": [
                    {
                        "scenePath": "res://assets/models/organelles/OxytoxyProteins.tscn"
                    }
                ],
                "density": 0.0001,
                "dissolves": false,
                "radius": 1,
                "chunkScale": 1,
                "mass": 7,
                "size": 10000,
                "ventAmount": 3,
                "damages": 10,
                "deleteOnTouch": true,
                "compounds": {}
            },
            "ironSmallChunk": {
                "name": "Small Iron Chunk",
                "meshes": [
                    {
                        "scenePath": "res://assets/models/IronRock1.tscn"
                    },
                    {
                        "scenePath": "res://assets/models/IronRock2.tscn"
                    },
                    {
                        "scenePath": "res://assets/models/Iron3.tscn"
                    },
                    {
                        "scenePath": "res://assets/models/Iron4.tscn"
                    }
                ],
                "density": 0,
                "dissolves": true,
                "radius": 1,
                "chunkScale": 1,
                "mass": 100,
                "size": 2,
                "ventAmount": 6,
                "damages": 0,
                "deleteOnTouch": false,
                "compounds": {
                    "iron": {
                        "amount": 200
                    }
                }
            },
            "ironBigChunk": {
                "name": "Big Iron Chunk",
                "meshes": [
                    {
                        "scenePath": "res://assets/models/Iron5.tscn"
                    }
                ],
                "density": 0,
                "dissolves": true,
                "radius": 10,
                "chunkScale": 1,
                "mass": 100,
                "size": 100,
                "ventAmount": 20,
                "damages": 0,
                "deleteOnTouch": false,
                "compounds": {
                    "iron": {
                        "amount": 60000
                    }
                }
            },
            "marineSnow": {
                "name": "Marine snow",
                "meshes": [
                    {
                        "scenePath": "res://assets/models/organelles/Oxytoxy.tscn"
                    },
                    {
                        "scenePath": "res://assets/models/organelles/Nucleus.tscn"
                    },
                    {
                        "scenePath": "res://assets/models/organelles/Chloroplast.tscn"
                    },
                    {
                        "scenePath": "res://assets/models/organelles/OxytoxyProteins.tscn"
                    },
                    {
                        "scenePath": "res://assets/models/organelles/Flagellum.tscn"
                    },
                    {
                        "scenePath": "res://assets/models/organelles/Chemoplast.tscn"
                    },
                    {
                        "scenePath": "res://assets/models/organelles/NitrogenFixingPlastid.tscn"
                    },
                    {
                        "scenePath": "res://assets/models/organelles/Metabolosome.tscn"
                    },
                    {
                        "scenePath": "res://assets/models/organelles/Chromatophore.tscn"
                    },
                    {
                        "scenePath": "res://assets/models/organelles/Vacuole.tscn"
                    },
                    {
                        "scenePath": "res://assets/models/organelles/Mitochondrion.tscn"
                    },
                    {
                        "scenePath": "res://assets/models/organelles/ChemoSynthesizingProteins.tscn"
                    },
                    {
                        "scenePath": "res://assets/models/organelles/Nitrogenase.tscn"
                    },
                    {
                        "scenePath": "res://assets/models/organelles/Rusticyanin.tscn"
                    }
                ],
                "density": 0.00002,
                "dissolves": true,
                "radius": 1,
                "chunkScale": 1,
                "mass": 7,
                "size": 2,
                "ventAmount": 3,
                "damages": 0,
                "deleteOnTouch": false,
                "compounds": {
                    "atp": {
                        "amount": 100
                    },
                    "ammonia": {
                        "amount": 100
                    },
                    "phosphates": {
                        "amount": 100
                    },
                    "glucose": {
                        "amount": 100
                    }
                }
            }
        },
        "averageTemperature": 2,
        "compounds": {
            "ammonia": {
                "amount": 200000,
                "density": 0.00002,
                "dissolved": 0
            },
            "glucose": {
                "amount": 250000,
                "density": 0.00002,
                "dissolved": 0
            },
            "phosphates": {
                "amount": 200000,
                "density": 0.00002,
                "dissolved": 0
            },
            "hydrogensulfide": {
                "amount": 0,
                "density": 0,
                "dissolved": 0
            },
            "oxygen": {
                "amount": 0,
                "density": 0,
                "dissolved": 0.21
            },
            "carbondioxide": {
                "amount": 0,
                "density": 0,
                "dissolved": 0.09
            },
            "nitrogen": {
                "amount": 0,
                "density": 0,
                "dissolved": 0.7
            },
            "sunlight": {
                "amount": 0,
                "density": 0,
                "dissolved": 0
            }
        }
    },
    "mesopelagic": {
        "name": "Mesopelagic",
        "background": "mesopelagic",
        "icon": "res://assets/textures/gui/bevel/mesopelagic.png",
        "skybox": "Thrive_meso_skybox",
        "skyboxLightIntensity": 0.5,
        "sunlight": {
            "color": {
                "r": 1,
                "g": 1,
                "b": 1
            },
            "intensity": 0.0001,
            "direction": {
                "x": 0.55,
                "y": -0.3,
                "z": 0.75
            },
            "sourceRadius": 0.5
        },
        "eyeAdaptation": {
            "min": 0.003,
            "max": 1.7
        },
        "chunks": {
            "floatingToxin": {
                "name": "Floating Hazard",
                "meshes": [
                    {
                        "scenePath": "res://assets/models/organelles/OxytoxyProteins.tscn"
                    }
                ],
                "density": 0.0001,
                "dissolves": false,
                "radius": 1,
                "chunkScale": 1,
                "mass": 7,
                "size": 10000,
                "ventAmount": 3,
                "damages": 10,
                "deleteOnTouch": true,
                "compounds": {}
            },
            "ironSmallChunk": {
                "name": "Small Iron Chunk",
                "meshes": [
                    {
                        "scenePath": "res://assets/models/IronRock1.tscn"
                    },
                    {
                        "scenePath": "res://assets/models/IronRock2.tscn"
                    },
                    {
                        "scenePath": "res://assets/models/Iron3.tscn"
                    },
                    {
                        "scenePath": "res://assets/models/Iron4.tscn"
                    }
                ],
                "density": 0.0005,
                "dissolves": true,
                "radius": 1,
                "chunkScale": 1,
                "mass": 100,
                "size": 2,
                "ventAmount": 6,
                "damages": 0,
                "deleteOnTouch": false,
                "compounds": {
                    "iron": {
                        "amount": 200
                    }
                }
            },
            "ironBigChunk": {
                "name": "Big Iron Chunk",
                "meshes": [
                    {
                        "scenePath": "res://assets/models/Iron5.tscn"
                    }
                ],
                "density": 0.00005,
                "dissolves": true,
                "radius": 10,
                "chunkScale": 1,
                "mass": 100,
                "size": 100,
                "ventAmount": 20,
                "damages": 0,
                "deleteOnTouch": false,
                "compounds": {
                    "iron": {
                        "amount": 60000
                    }
                }
            },
            "marineSnow": {
                "name": "Marine snow",
                "meshes": [
                    {
                        "scenePath": "res://assets/models/organelles/Oxytoxy.tscn"
                    },
                    {
                        "scenePath": "res://assets/models/organelles/Nucleus.tscn"
                    },
                    {
                        "scenePath": "res://assets/models/organelles/Chloroplast.tscn"
                    },
                    {
                        "scenePath": "res://assets/models/organelles/OxytoxyProteins.tscn"
                    },
                    {
                        "scenePath": "res://assets/models/organelles/Flagellum.tscn"
                    },
                    {
                        "scenePath": "res://assets/models/organelles/Chemoplast.tscn"
                    },
                    {
                        "scenePath": "res://assets/models/organelles/NitrogenFixingPlastid.tscn"
                    },
                    {
                        "scenePath": "res://assets/models/organelles/Metabolosome.tscn"
                    },
                    {
                        "scenePath": "res://assets/models/organelles/Chromatophore.tscn"
                    },
                    {
                        "scenePath": "res://assets/models/organelles/Vacuole.tscn"
                    },
                    {
                        "scenePath": "res://assets/models/organelles/Mitochondrion.tscn"
                    },
                    {
                        "scenePath": "res://assets/models/organelles/ChemoSynthesizingProteins.tscn"
                    },
                    {
                        "scenePath": "res://assets/models/organelles/Nitrogenase.tscn"
                    },
                    {
                        "scenePath": "res://assets/models/organelles/Rusticyanin.tscn"
                    }
                ],
                "density": 0.00002,
                "dissolves": true,
                "radius": 1,
                "chunkScale": 1,
                "mass": 7,
                "size": 2,
                "ventAmount": 3,
                "damages": 0,
                "deleteOnTouch": false,
                "compounds": {
                    "atp": {
                        "amount": 100
                    },
                    "ammonia": {
                        "amount": 100
                    },
                    "phosphates": {
                        "amount": 100
                    },
                    "glucose": {
                        "amount": 100
                    }
                }
            }
        },
        "averageTemperature": 2,
        "compounds": {
            "ammonia": {
                "amount": 200000,
                "density": 0.00002,
                "dissolved": 0
            },
            "glucose": {
                "amount": 250000,
                "density": 0.00002,
                "dissolved": 0
            },
            "phosphates": {
                "amount": 200000,
                "density": 0.00002,
                "dissolved": 0
            },
            "hydrogensulfide": {
                "amount": 0,
                "density": 0,
                "dissolved": 0
            },
            "oxygen": {
                "amount": 0,
                "density": 0,
                "dissolved": 0.21
            },
            "carbondioxide": {
                "amount": 0,
                "density": 0,
                "dissolved": 0.09
            },
            "nitrogen": {
                "amount": 0,
                "density": 0,
                "dissolved": 0.7
            },
            "sunlight": {
                "amount": 0,
                "density": 0,
                "dissolved": 0.01
            }
        }
    },
    "coastal": {
        "name": "Coastal",
        "background": "coastal",
        "icon": "res://assets/textures/gui/bevel/shallow.png",
        "skybox": "Thrive_shallow_skybox",
        "skyboxLightIntensity": 0.5,
        "sunlight": {
            "color": {
                "r": 1,
                "g": 1,
                "b": 1
            },
            "intensity": 0.0001,
            "direction": {
                "x": 0.55,
                "y": -0.3,
                "z": 0.75
            },
            "sourceRadius": 0.5
        },
        "eyeAdaptation": {
            "min": 0.003,
            "max": 2
        },
        "chunks": {
            "floatingToxin": {
                "name": "Floating Hazard",
                "meshes": [
                    {
                        "scenePath": "res://assets/models/organelles/OxytoxyProteins.tscn"
                    }
                ],
                "density": 0.0001,
                "dissolves": false,
                "radius": 1,
                "chunkScale": 1,
                "mass": 7,
                "size": 10000,
                "ventAmount": 3,
                "damages": 10,
                "deleteOnTouch": true,
                "compounds": {}
            },
            "ironSmallChunk": {
                "name": "Small Iron Chunk",
                "meshes": [
                    {
                        "scenePath": "res://assets/models/IronRock1.tscn"
                    },
                    {
                        "scenePath": "res://assets/models/IronRock2.tscn"
                    },
                    {
                        "scenePath": "res://assets/models/Iron3.tscn"
                    },
                    {
                        "scenePath": "res://assets/models/Iron4.tscn"
                    }
                ],
                "density": 0.00005,
                "dissolves": true,
                "radius": 1,
                "chunkScale": 1,
                "mass": 100,
                "size": 2,
                "ventAmount": 6,
                "damages": 0,
                "deleteOnTouch": false,
                "compounds": {
                    "iron": {
                        "amount": 200
                    }
                }
            },
            "ironBigChunk": {
                "name": "Big Iron Chunk",
                "meshes": [
                    {
                        "scenePath": "res://assets/models/Iron5.tscn"
                    }
                ],
                "density": 0.00005,
                "dissolves": true,
                "radius": 10,
                "chunkScale": 1,
                "mass": 100,
                "size": 100,
                "ventAmount": 20,
                "damages": 0,
                "deleteOnTouch": false,
                "compounds": {
                    "iron": {
                        "amount": 60000
                    }
                }
            }
        },
        "averageTemperature": 17,
        "compounds": {
            "ammonia": {
                "amount": 200000,
                "density": 0.00002,
                "dissolved": 0
            },
            "glucose": {
                "amount": 250000,
                "density": 0.00002,
                "dissolved": 0
            },
            "phosphates": {
                "amount": 200000,
                "density": 0.00002,
                "dissolved": 0
            },
            "hydrogensulfide": {
                "amount": 0,
                "density": 0,
                "dissolved": 0
            },
            "oxygen": {
                "amount": 0,
                "density": 0,
                "dissolved": 0.21
            },
            "carbondioxide": {
                "amount": 0,
                "density": 0,
                "dissolved": 0.09
            },
            "nitrogen": {
                "amount": 0,
                "density": 0,
                "dissolved": 0.7
            },
            "sunlight": {
                "amount": 0,
                "density": 0,
                "dissolved": 1
            }
        }
    },
    "underwater_cave": {
        "name": "UnderwaterCave",
        "background": "cave",
        "icon": "res://assets/textures/gui/bevel/cave.png",
        "skybox": "Thrive_cave_skybox",
        "skyboxLightIntensity": 0.5,
        "sunlight": {
            "color": {
                "r": 1,
                "g": 1,
                "b": 1
            },
            "intensity": 0.0001,
            "direction": {
                "x": 0.55,
                "y": -0.3,
                "z": 0.75
            },
            "sourceRadius": 0.5
        },
        "eyeAdaptation": {
            "min": 0.003,
            "max": 0.8
        },
        "chunks": {
            "floatingToxin": {
                "name": "Floating Hazard",
                "meshes": [
                    {
                        "scenePath": "res://assets/models/organelles/OxytoxyProteins.tscn"
                    }
                ],
                "density": 0.001,
                "dissolves": false,
                "radius": 1,
                "chunkScale": 1,
                "mass": 7,
                "size": 10000,
                "ventAmount": 3,
                "damages": 10,
                "deleteOnTouch": true,
                "compounds": {}
            },
            "ironSmallChunk": {
                "name": "Small Iron Chunk",
                "meshes": [
                    {
                        "scenePath": "res://assets/models/IronRock1.tscn"
                    },
                    {
                        "scenePath": "res://assets/models/IronRock2.tscn"
                    },
                    {
                        "scenePath": "res://assets/models/Iron3.tscn"
                    },
                    {
                        "scenePath": "res://assets/models/Iron4.tscn"
                    }
                ],
                "density": 0.0001,
                "dissolves": true,
                "radius": 1,
                "chunkScale": 1,
                "mass": 100,
                "size": 2,
                "ventAmount": 6,
                "damages": 0,
                "deleteOnTouch": false,
                "compounds": {
                    "iron": {
                        "amount": 200
                    }
                }
            },
            "ironBigChunk": {
                "name": "Big Iron Chunk",
                "meshes": [
                    {
                        "scenePath": "res://assets/models/Iron5.tscn"
                    }
                ],
                "density": 0.0001,
                "dissolves": true,
                "radius": 10,
                "chunkScale": 1,
                "mass": 100,
                "size": 100,
                "ventAmount": 20,
                "damages": 0,
                "deleteOnTouch": false,
                "compounds": {
                    "iron": {
                        "amount": 60000
                    }
                }
            }
        },
        "averageTemperature": 23,
        "compounds": {
            "ammonia": {
                "amount": 200000,
                "density": 0.00002,
                "dissolved": 0
            },
            "glucose": {
                "amount": 250000,
                "density": 0.00002,
                "dissolved": 0
            },
            "phosphates": {
                "amount": 200000,
                "density": 0.00002,
                "dissolved": 0
            },
            "hydrogensulfide": {
                "amount": 225000,
                "density": 0.00002,
                "dissolved": 0
            },
            "oxygen": {
                "amount": 0,
                "density": 0,
                "dissolved": 0.21
            },
            "carbondioxide": {
                "amount": 0,
                "density": 0,
                "dissolved": 0.09
            },
            "nitrogen": {
                "amount": 0,
                "density": 0,
                "dissolved": 0.7
            },
            "sunlight": {
                "amount": 0,
                "density": 0,
                "dissolved": 0
            }
        }
    },
    "ice_shelf": {
        "name": "IceShelf",
        "background": "iceshelf",
        "icon": "res://assets/textures/gui/bevel/iceshelf.png",
        "skybox": "Thrive_iceshelf_skybox",
        "skyboxLightIntensity": 0.5,
        "sunlight": {
            "color": {
                "r": 1,
                "g": 1,
                "b": 1
            },
            "intensity": 0.0001,
            "direction": {
                "x": 0.55,
                "y": -0.3,
                "z": 0.75
            },
            "sourceRadius": 0.5
        },
        "eyeAdaptation": {
            "min": 0.003,
            "max": 2
        },
        "chunks": {
            "floatingToxin": {
                "name": "Floating Hazard",
                "meshes": [
                    {
                        "scenePath": "res://assets/models/organelles/OxytoxyProteins.tscn"
                    }
                ],
                "density": 0.0005,
                "dissolves": false,
                "radius": 1,
                "chunkScale": 1,
                "mass": 7,
                "size": 10000,
                "ventAmount": 3,
                "damages": 10,
                "deleteOnTouch": true,
                "compounds": {}
            },
            "ironSmallChunk": {
                "name": "Small Iron Chunk",
                "meshes": [
                    {
                        "scenePath": "res://assets/models/IronRock1.tscn"
                    },
                    {
                        "scenePath": "res://assets/models/IronRock2.tscn"
                    },
                    {
                        "scenePath": "res://assets/models/Iron3.tscn"
                    },
                    {
                        "scenePath": "res://assets/models/Iron4.tscn"
                    }
                ],
                "density": 0.0002,
                "dissolves": true,
                "radius": 1,
                "chunkScale": 1,
                "mass": 100,
                "size": 2,
                "ventAmount": 6,
                "damages": 0,
                "deleteOnTouch": false,
                "compounds": {
                    "iron": {
                        "amount": 200
                    }
                }
            },
            "iceShard": {
                "name": "Ice Shard",
                "meshes": [
                    {
                        "scenePath": "res://assets/models/Iceshard1.tscn"
                    }
                ],
                "density": 0.002,
                "dissolves": false,
                "radius": 1,
                "chunkScale": 1,
                "mass": 100,
                "size": 1000,
                "ventAmount": 3,
                "damages": 0.5,
                "deleteOnTouch": false,
                "compounds": {}
            },
            "ironBigChunk": {
                "name": "Big Iron Chunk",
                "meshes": [
                    {
                        "scenePath": "res://assets/models/Iron5.tscn"
                    }
                ],
                "density": 0.0002,
                "dissolves": true,
                "radius": 10,
                "chunkScale": 1,
                "mass": 100,
                "size": 100,
                "ventAmount": 20,
                "damages": 0,
                "deleteOnTouch": false,
                "compounds": {
                    "iron": {
                        "amount": 60000
                    }
                }
            }
        },
        "averageTemperature": -1,
        "compounds": {
            "ammonia": {
                "amount": 200000,
                "density": 0.00002,
                "dissolved": 0
            },
            "glucose": {
                "amount": 250000,
                "density": 0.00002,
                "dissolved": 0
            },
            "phosphates": {
                "amount": 200000,
                "density": 0.00002,
                "dissolved": 0
            },
            "hydrogensulfide": {
                "amount": 0,
                "density": 0,
                "dissolved": 0
            },
            "oxygen": {
                "amount": 0,
                "density": 0,
                "dissolved": 0.21
            },
            "carbondioxide": {
                "amount": 0,
                "density": 0,
                "dissolved": 0.09
            },
            "nitrogen": {
                "amount": 0,
                "density": 0,
                "dissolved": 0.7
            },
            "sunlight": {
                "amount": 0,
                "density": 0,
                "dissolved": 0.5
            }
        }
    },
    "estuary": {
        "name": "Estuary",
        "background": "estuary",
        "icon": "res://assets/textures/gui/bevel/estuary.png",
        "skybox": "Thrive_estuary_skybox",
        "skyboxLightIntensity": 0.5,
        "sunlight": {
            "color": {
                "r": 1,
                "g": 1,
                "b": 1
            },
            "intensity": 0.0001,
            "direction": {
                "x": 0.55,
                "y": -0.3,
                "z": 0.75
            },
            "sourceRadius": 0.5
        },
        "eyeAdaptation": {
            "min": 0.003,
            "max": 2
        },
        "chunks": {
            "floatingToxin": {
                "name": "Floating Hazard",
                "meshes": [
                    {
                        "scenePath": "res://assets/models/organelles/OxytoxyProteins.tscn"
                    }
                ],
                "density": 0.0001,
                "dissolves": false,
                "radius": 1,
                "chunkScale": 1,
                "mass": 7,
                "size": 10000,
                "ventAmount": 3,
                "damages": 10,
                "deleteOnTouch": true,
                "compounds": {}
            },
            "ironSmallChunk": {
                "name": "Small Iron Chunk",
                "meshes": [
                    {
                        "scenePath": "res://assets/models/IronRock1.tscn"
                    },
                    {
                        "scenePath": "res://assets/models/IronRock2.tscn"
                    },
                    {
                        "scenePath": "res://assets/models/Iron3.tscn"
                    },
                    {
                        "scenePath": "res://assets/models/Iron4.tscn"
                    }
                ],
                "density": 0.00005,
                "dissolves": true,
                "radius": 1,
                "chunkScale": 1,
                "mass": 100,
                "size": 2,
                "ventAmount": 6,
                "damages": 0,
                "deleteOnTouch": false,
                "compounds": {
                    "iron": {
                        "amount": 200
                    }
                }
            },
            "ironBigChunk": {
                "name": "Big Iron Chunk",
                "meshes": [
                    {
                        "scenePath": "res://assets/models/Iron5.tscn"
                    }
                ],
                "density": 0.00005,
                "dissolves": true,
                "radius": 10,
                "chunkScale": 1,
                "mass": 100,
                "size": 100,
                "ventAmount": 20,
                "damages": 0,
                "deleteOnTouch": false,
                "compounds": {
                    "iron": {
                        "amount": 60000
                    }
                }
            }
        },
        "averageTemperature": 17,
        "compounds": {
            "ammonia": {
                "amount": 200000,
                "density": 0.00002,
                "dissolved": 0
            },
            "glucose": {
                "amount": 250000,
                "density": 0.00002,
                "dissolved": 0
            },
            "phosphates": {
                "amount": 200000,
                "density": 0.00002,
                "dissolved": 0
            },
            "hydrogensulfide": {
                "amount": 0,
                "density": 0,
                "dissolved": 0
            },
            "oxygen": {
                "amount": 0,
                "density": 0,
                "dissolved": 0.21
            },
            "carbondioxide": {
                "amount": 0,
                "density": 0,
                "dissolved": 0.09
            },
            "nitrogen": {
                "amount": 0,
                "density": 0,
                "dissolved": 0.78
            },
            "sunlight": {
                "amount": 0,
                "density": 0,
                "dissolved": 1.5
            }
        }
    },
    "seafloor": {
        "name": "Sea Floor",
        "background": "seafloor",
        "icon": "res://assets/textures/gui/bevel/bathyFloor.png",
        "skybox": "Thrive_seafloor_skybox",
        "skyboxLightIntensity": 0.5,
        "sunlight": {
            "color": {
                "r": 1,
                "g": 1,
                "b": 1
            },
            "intensity": 0.0001,
            "direction": {
                "x": 0.55,
                "y": -0.3,
                "z": 0.75
            },
            "sourceRadius": 0.5
        },
        "eyeAdaptation": {
            "min": 0.003,
            "max": 1
        },
        "chunks": {
            "floatingToxin": {
                "name": "Floating Hazard",
                "meshes": [
                    {
                        "scenePath": "res://assets/models/organelles/OxytoxyProteins.tscn"
                    }
                ],
                "density": 0.0001,
                "dissolves": false,
                "radius": 1,
                "chunkScale": 1,
                "mass": 7,
                "size": 10000,
                "ventAmount": 3,
                "damages": 10,
                "deleteOnTouch": true,
                "compounds": {}
            },
            "ironSmallChunk": {
                "name": "Small Iron Chunk",
                "meshes": [
                    {
                        "scenePath": "res://assets/models/IronRock1.tscn"
                    },
                    {
                        "scenePath": "res://assets/models/IronRock2.tscn"
                    },
                    {
                        "scenePath": "res://assets/models/Iron3.tscn"
                    },
                    {
                        "scenePath": "res://assets/models/Iron4.tscn"
                    }
                ],
                "density": 0.00005,
                "dissolves": true,
                "radius": 1,
                "chunkScale": 1,
                "mass": 100,
                "size": 2,
                "ventAmount": 6,
                "damages": 0,
                "deleteOnTouch": false,
                "compounds": {
                    "iron": {
                        "amount": 200
                    }
                }
            },
            "ironBigChunk": {
                "name": "Big Iron Chunk",
                "meshes": [
                    {
                        "scenePath": "res://assets/models/Iron5.tscn"
                    }
                ],
                "density": 0.00005,
                "dissolves": true,
                "radius": 10,
                "chunkScale": 1,
                "mass": 100,
                "size": 100,
                "ventAmount": 20,
                "damages": 0,
                "deleteOnTouch": false,
                "compounds": {
                    "iron": {
                        "amount": 60000
                    }
                }
            },
            "marineSnow": {
                "name": "Marine snow",
                "meshes": [
                    {
                        "scenePath": "res://assets/models/organelles/Oxytoxy.tscn"
                    },
                    {
                        "scenePath": "res://assets/models/organelles/Nucleus.tscn"
                    },
                    {
                        "scenePath": "res://assets/models/organelles/Chloroplast.tscn"
                    },
                    {
                        "scenePath": "res://assets/models/organelles/OxytoxyProteins.tscn"
                    },
                    {
                        "scenePath": "res://assets/models/organelles/Flagellum.tscn"
                    },
                    {
                        "scenePath": "res://assets/models/organelles/Chemoplast.tscn"
                    },
                    {
                        "scenePath": "res://assets/models/organelles/NitrogenFixingPlastid.tscn"
                    },
                    {
                        "scenePath": "res://assets/models/organelles/Metabolosome.tscn"
                    },
                    {
                        "scenePath": "res://assets/models/organelles/Chromatophore.tscn"
                    },
                    {
                        "scenePath": "res://assets/models/organelles/Vacuole.tscn"
                    },
                    {
                        "scenePath": "res://assets/models/organelles/Mitochondrion.tscn"
                    },
                    {
                        "scenePath": "res://assets/models/organelles/ChemoSynthesizingProteins.tscn"
                    },
                    {
                        "scenePath": "res://assets/models/organelles/Nitrogenase.tscn"
                    },
                    {
                        "scenePath": "res://assets/models/organelles/Rusticyanin.tscn"
                    }
                ],
                "density": 0.00004,
                "dissolves": true,
                "radius": 1,
                "chunkScale": 1,
                "mass": 7,
                "size": 2,
                "ventAmount": 3,
                "damages": 0,
                "deleteOnTouch": false,
                "compounds": {
                    "atp": {
                        "amount": 100
                    },
                    "ammonia": {
                        "amount": 100
                    },
                    "phosphates": {
                        "amount": 100
                    },
                    "glucose": {
                        "amount": 100
                    }
                }
            }
        },
        "averageTemperature": 4,
        "compounds": {
            "ammonia": {
                "amount": 200000,
                "density": 0.00002,
                "dissolved": 0
            },
            "glucose": {
                "amount": 250000,
                "density": 0.00002,
                "dissolved": 0
            },
            "phosphates": {
                "amount": 200000,
                "density": 0.00002,
                "dissolved": 0
            },
            "hydrogensulfide": {
                "amount": 0,
                "density": 0,
                "dissolved": 0
            },
            "oxygen": {
                "amount": 0,
                "density": 0,
                "dissolved": 0.21
            },
            "carbondioxide": {
                "amount": 0,
                "density": 0,
                "dissolved": 0.09
            },
            "nitrogen": {
                "amount": 0,
                "density": 0,
                "dissolved": 0.7
            },
            "sunlight": {
                "amount": 0,
                "density": 0,
                "dissolved": 0
            }
        }
    }
}